setup.cfg
setup.py
tenthousandfeet/__init__.py
tenthousandfeet/version.py
tenthousandfeet.egg-info/PKG-INFO
tenthousandfeet.egg-info/SOURCES.txt
tenthousandfeet.egg-info/dependency_links.txt
tenthousandfeet.egg-info/requires.txt
tenthousandfeet.egg-info/top_level.txt
tests/__init__.py
tests/test_auth.py
tests/test_collection.py
tests/test_dates.py
tests/test_errors.py