Metadata-Version: 1.1
Name: tenthousandfeet
Version: 0.1.1
Summary: A client for the 10000ft.com service (http://10kft.github.io/api-documentation/).
Home-page: https://github.com/cooper-software/python-10000ft
Author: Elisha Fitch-Cook
Author-email: elisha@cooper.com
License: UNKNOWN
Download-URL: https://github.com/cooper-software/python-10000ft/tarball/0.1.1
Platform: UNKNOWN
